pydanticio/__init__.py
pydanticio/backends/__init__.py
pydanticio/backends/cbor.py
pydanticio/backends/cbor_stub.py
pydanticio/backends/csv.py
pydanticio/backends/json.py
pydanticio/backends/json_lines.py
pydanticio/backends/messagepack.py
pydanticio/backends/messagepack_stub.py
pydanticio/backends/toml.py
pydanticio/backends/toml_stub.py
pydanticio/backends/yaml.py
pydanticio/backends/yaml_stub.py
pydanticio/utils.py
pydanticio/version.py
pydanticio-0.5.0.dist-info/WHEEL
pydanticio-0.5.0.dist-info/METADATA
pydanticio-0.5.0.dist-info/RECORD
