Metadata-Version: 2.3
Name: pydanticio
Version: 0.5.0
Summary: A Tiny file IO utility library for Python powered by Pydantic
Keywords: pydantic,io,file,utility,library
Author: 杜世橋 Du Shiqiao
Author-email: 杜世橋 Du Shiqiao <lucidfrontier.45@gmail.com>
License: MIT
Classifier: Intended Audience :: Developers
Classifier: Topic :: Software Development :: Libraries
Classifier: Topic :: Software Development :: Libraries :: Python Modules
Classifier: Topic :: Utilities
Classifier: License :: OSI Approved :: MIT License
Classifier: Programming Language :: Python :: 3
Classifier: Programming Language :: Python :: 3.12
Classifier: Programming Language :: Python :: 3.13
Classifier: Programming Language :: Python :: 3.14
Classifier: Programming Language :: Python :: 3 :: Only
Requires-Dist: pydantic>=2.5.0
Requires-Dist: cbor2>=5.8.0 ; extra == 'cbor'
Requires-Dist: msgpack>=1.1.2 ; extra == 'messagepack'
Requires-Dist: tomlkit>=0.14.0 ; extra == 'toml'
Requires-Dist: pyyaml>=5.1.0 ; extra == 'yaml'
Requires-Python: >=3.12
Project-URL: repository, https://github.com/lucidfrontier45/pydanticio
Provides-Extra: cbor
Provides-Extra: messagepack
Provides-Extra: toml
Provides-Extra: yaml
